{
    "version": "0.30.53",
    "homepage": "http://fleet.moe/",
    "description": "Who Calls The Fleet? ——Diablohu",
    "license": "MIT License",
    "architecture": {
        "64bit": {
            "url": "https://github.com/TeamFleet/WhoCallsTheFleet/releases/download/v0.30.53/WhoCallsTheFleet-0.30.53-win64.zip",
            "hash": "30a6369f2ebc789f627f6d93587e2b7bed997b6137b42a25b112d606eb42b935"
        }
    },
    "bin": "WhoCallsTheFleet.exe",
    "shortcuts": [
        [
            "WhoCallsTheFleet.exe",
            "WhoCallsTheFleet"
        ]
    ],
    "checkver": {
        "github": "https://github.com/TeamFleet/WhoCallsTheFleet"
    },
    "autoupdate": {
        "architecture": {
            "64bit": {
                "url": "https://github.com/TeamFleet/WhoCallsTheFleet/releases/download/v$version/WhoCallsTheFleet-$version-win64.zip"
            }
        }
    }
}
